{
    "$schema": [
        "http://schemata.hasdai.org/historic-persons/historic-company-entry-v1.0.1.json"
    ],
    "id": "BSCC-120-1951-3-B109",
    "status": "bscc entry",
    "date": {
        "ref": "1951"
    },
    "transcription": {
        "original": "109. Braillard (Charles), 23, avenue Villamont, Lausanne. A 1376, C 441.",
        "corrected": "109. Braillard (Charles), 23, avenue Villamont, Lausanne. A 1376, C 441"
    },
    "source": {
        "id": "PLEASE_FILL_IN",
        "title": "INDEX OF SWISS AGENTS REPRESENTING UNITED KINGDOM FIRMS",
        "selector": {
            "page": 120,
            "canvas": "http://localhost:8182/iiif/3/0120.jpg/full/max/0/default.jpg",
            "fragment": "http://localhost:8182/iiif/3/0120.jpg/159,440,1348,34/max/0/default.jpg",
            "xywh": "159, 440, 1348, 34"
        }
    },
    "short_id": "B109",
    "label": "Braillard (Charles)",
    "connection": [
        {
            "to": [
                {
                    "id": "BSCC-1951-120-3-A1376",
                    "short_id": "A1376"
                }
            ],
            "what": [
                {
                    "id": "BSCC-1951-120-3-C441",
                    "short_id": "C441"
                }
            ],
            "description": "The swiss company B109 trades with the british company A1376 in the goods C441"
        }
    ],
    "organisation": [
        {
            "transcription": "Braillard (Charles)"
        }
    ],
    "location": [
        {
            "id": "2659994",
            "lat": "46.516",
            "lng": "6.63282",
            "country": {
                "id": "2658434",
                "inferred": "Switzerland",
                "code": "CH"
            },
            "scheme": "geonames.org",
            "inferred": "Lausanne",
            "transcription": "23, avenue Villamont, Lausanne. "
        }
    ],
    "meta": {
        "version": 1,
        "partOf": "BSCC-1951",
        "generated": "2022-11-18",
        "actions": [
            {
                "actor": {
                    "id": "0000-0002-9541-1202",
                    "scheme": "ORCID",
                    "name": "Sorin Marti"
                },
                "date": "2022-11-18",
                "summary": "Parsed by v.2021-10-31-0 of the BSCC-Parser",
                "classifiedAction": "auto_parse_bscc"
            }
        ]
    }
}