{
    "$schema": [
        "http://schemata.hasdai.org/historic-persons/historic-company-entry-v1.0.1.json"
    ],
    "id": "BSCC-98-1951-6-A2014",
    "status": "bscc entry",
    "date": {
        "ref": "1951"
    },
    "transcription": {
        "original": "2014. Veedip Ltd., Slough. B 724, C 1302.",
        "corrected": "2014. Veedip Ltd., Slough. B 724, C 1302"
    },
    "source": {
        "id": "PLEASE_FILL_IN",
        "title": "INDEX OF SWISS AGENTS REPRESENTING UNITED KINGDOM FIRMS",
        "selector": {
            "page": 98,
            "canvas": "http://localhost:8182/iiif/3/0098.jpg/full/max/0/default.jpg",
            "fragment": "http://localhost:8182/iiif/3/0098.jpg/180,467,1270,40/max/0/default.jpg",
            "xywh": "180, 467, 1270, 40"
        }
    },
    "short_id": "A2014",
    "label": "Veedip Ltd.",
    "connection": [
        {
            "to": [
                {
                    "id": "BSCC-1951-98-6-B724",
                    "short_id": "B724"
                }
            ],
            "what": [
                {
                    "id": "BSCC-1951-98-6-C1302",
                    "short_id": "C1302"
                }
            ],
            "description": "The british company A2014 trades with the swiss company B724 in the goods C1302"
        }
    ],
    "organisation": [
        {
            "transcription": "Veedip Ltd."
        }
    ],
    "location": [
        {
            "id": "2637627",
            "lat": "51.50949",
            "lng": "-0.59541",
            "country": {
                "id": "2635167",
                "inferred": "United Kingdom",
                "code": "GB"
            },
            "scheme": "geonames.org",
            "inferred": "Slough",
            "transcription": " Slough. "
        }
    ],
    "meta": {
        "version": 1,
        "partOf": "BSCC-1951",
        "generated": "2022-11-18",
        "actions": [
            {
                "actor": {
                    "id": "0000-0002-9541-1202",
                    "scheme": "ORCID",
                    "name": "Sorin Marti"
                },
                "date": "2022-11-18",
                "summary": "Parsed by v.2021-10-31-0 of the BSCC-Parser",
                "classifiedAction": "auto_parse_bscc"
            }
        ]
    }
}