{
    "$schema": [
        "http://schemata.hasdai.org/historic-persons/historic-company-entry-v1.0.1.json"
    ],
    "id": "BSCC-80-1951-12-A1481",
    "status": "bscc entry",
    "date": {
        "ref": "1951"
    },
    "transcription": {
        "original": "1481. Parker Pipe Co. Ltd., London W 11. B 196, C 1453.",
        "corrected": "1481. Parker Pipe Co. Ltd., London W 11. B 196, C 1453"
    },
    "source": {
        "id": "PLEASE_FILL_IN",
        "title": "INDEX OF SWISS AGENTS REPRESENTING UNITED KINGDOM FIRMS",
        "selector": {
            "page": 80,
            "canvas": "http://localhost:8182/iiif/3/0080.jpg/full/max/0/default.jpg",
            "fragment": "http://localhost:8182/iiif/3/0080.jpg/200,718,1303,40/max/0/default.jpg",
            "xywh": "200, 718, 1303, 40"
        }
    },
    "short_id": "A1481",
    "label": "Parker Pipe Co. Ltd.",
    "connection": [
        {
            "to": [
                {
                    "id": "BSCC-1951-80-12-B196",
                    "short_id": "B196"
                }
            ],
            "what": [
                {
                    "id": "BSCC-1951-80-12-C1453",
                    "short_id": "C1453"
                }
            ],
            "description": "The british company A1481 trades with the swiss company B196 in the goods C1453"
        }
    ],
    "organisation": [
        {
            "transcription": "Parker Pipe Co. Ltd."
        }
    ],
    "location": [
        {
            "id": "2643743",
            "lat": "51.50853",
            "lng": "-0.12574",
            "country": {
                "id": "2635167",
                "inferred": "United Kingdom",
                "code": "GB"
            },
            "scheme": "geonames.org",
            "inferred": "London",
            "transcription": " London W 11. "
        }
    ],
    "meta": {
        "version": 1,
        "partOf": "BSCC-1951",
        "generated": "2022-11-18",
        "actions": [
            {
                "actor": {
                    "id": "0000-0002-9541-1202",
                    "scheme": "ORCID",
                    "name": "Sorin Marti"
                },
                "date": "2022-11-18",
                "summary": "Parsed by v.2021-10-31-0 of the BSCC-Parser",
                "classifiedAction": "auto_parse_bscc"
            }
        ]
    }
}