{
    "$schema": [
        "http://schemata.hasdai.org/historic-persons/historic-company-entry-v1.0.1.json"
    ],
    "id": "BSCC-44-1951-16-A689",
    "status": "bscc entry",
    "date": {
        "ref": "1951"
    },
    "transcription": {
        "original": "689. Fidler (H. & L.) Ltd., Salford. B 299, C 1157.",
        "corrected": "689. Fidler (H. & L.) Ltd., Salford. B 299, C 1157"
    },
    "source": {
        "id": "PLEASE_FILL_IN",
        "title": "INDEX OF SWISS AGENTS REPRESENTING UNITED KINGDOM FIRMS",
        "selector": {
            "page": 44,
            "canvas": "http://localhost:8182/iiif/3/0044.jpg/full/max/0/default.jpg",
            "fragment": "http://localhost:8182/iiif/3/0044.jpg/189,926,1269,43/max/0/default.jpg",
            "xywh": "189, 926, 1269, 43"
        }
    },
    "short_id": "A689",
    "label": "Fidler (H. & L.) Ltd.",
    "connection": [
        {
            "to": [
                {
                    "id": "BSCC-1951-44-16-B299",
                    "short_id": "B299"
                }
            ],
            "what": [
                {
                    "id": "BSCC-1951-44-16-C1157",
                    "short_id": "C1157"
                }
            ],
            "description": "The british company A689 trades with the swiss company B299 in the goods C1157"
        }
    ],
    "organisation": [
        {
            "transcription": "Fidler (H. & L.) Ltd."
        }
    ],
    "location": [
        {
            "id": "2638671",
            "lat": "53.48771",
            "lng": "-2.29042",
            "country": {
                "id": "2635167",
                "inferred": "United Kingdom",
                "code": "GB"
            },
            "scheme": "geonames.org",
            "inferred": "Salford",
            "transcription": " Salford. "
        }
    ],
    "meta": {
        "version": 1,
        "partOf": "BSCC-1951",
        "generated": "2022-11-18",
        "actions": [
            {
                "actor": {
                    "id": "0000-0002-9541-1202",
                    "scheme": "ORCID",
                    "name": "Sorin Marti"
                },
                "date": "2022-11-18",
                "summary": "Parsed by v.2021-10-31-0 of the BSCC-Parser",
                "classifiedAction": "auto_parse_bscc"
            }
        ]
    }
}