{
    "$schema": [
        "http://schemata.hasdai.org/historic-persons/historic-company-entry-v1.0.1.json"
    ],
    "id": "BSCC-26-1951-38-A312",
    "status": "bscc entry",
    "date": {
        "ref": "1951"
    },
    "transcription": {
        "original": "312. British Vacuum Cleaner & Engineering Co. Ltd., Leatherhead. B 43, C 523.",
        "corrected": "312. British Vacuum Cleaner & Engineering Co. Ltd., Leatherhead. B 43, C 523"
    },
    "source": {
        "id": "PLEASE_FILL_IN",
        "title": "INDEX OF SWISS AGENTS REPRESENTING UNITED KINGDOM FIRMS",
        "selector": {
            "page": 26,
            "canvas": "http://localhost:8182/iiif/3/0026.jpg/full/max/0/default.jpg",
            "fragment": "http://localhost:8182/iiif/3/0026.jpg/189,1968,1290,43/max/0/default.jpg",
            "xywh": "189, 1968, 1290, 43"
        }
    },
    "short_id": "A312",
    "label": "British Vacuum Cleaner & Engineering Co. Ltd.",
    "connection": [
        {
            "to": [
                {
                    "id": "BSCC-1951-26-38-B43",
                    "short_id": "B43"
                }
            ],
            "what": [
                {
                    "id": "BSCC-1951-26-38-C523",
                    "short_id": "C523"
                }
            ],
            "description": "The british company A312 trades with the swiss company B43 in the goods C523"
        }
    ],
    "organisation": [
        {
            "transcription": "British Vacuum Cleaner & Engineering Co. Ltd."
        }
    ],
    "location": [
        {
            "id": "2644726",
            "lat": "51.29652",
            "lng": "-0.3338",
            "country": {
                "id": "2635167",
                "inferred": "United Kingdom",
                "code": "GB"
            },
            "scheme": "geonames.org",
            "inferred": "Leatherhead",
            "transcription": " Leatherhead. "
        }
    ],
    "meta": {
        "version": 1,
        "partOf": "BSCC-1951",
        "generated": "2022-10-26",
        "actions": [
            {
                "actor": {
                    "id": "0000-0002-9541-1202",
                    "scheme": "ORCID",
                    "name": "Sorin Marti"
                },
                "date": "2022-10-26",
                "summary": "Parsed by v.2021-10-31-0 of the BSCC-Parser",
                "classifiedAction": "auto_parse_bscc"
            }
        ]
    }
}