{
    "$schema": [
        "http://schemata.hasdai.org/historic-persons/historic-company-entry-v1.0.1.json"
    ],
    "id": "BSCC-48-1951-20-A784",
    "status": "bscc entry",
    "date": {
        "ref": "1951"
    },
    "transcription": {
        "original": "﻿784. Glenfield & Kennedy Ltd., Kilmarnock. B 397, C 258, 684, 726, 730, 737.",
        "corrected": "784. Glenfield & Kennedy Ltd., Kilmarnock. B 397, C 258, 684, 726, 730, 737"
    },
    "source": {
        "id": "PLEASE_FILL_IN",
        "title": "INDEX OF SWISS AGENTS REPRESENTING UNITED KINGDOM FIRMS",
        "selector": {
            "page": 48,
            "canvas": "http://localhost:8182/iiif/3/0048.jpg/full/max/0/default.jpg",
            "fragment": "http://localhost:8182/iiif/3/0048.jpg/200,1041,1259,41/max/0/default.jpg",
            "xywh": "200, 1041, 1259, 41"
        }
    },
    "short_id": "A784",
    "label": "Glenfield & Kennedy Ltd.",
    "connection": [
        {
            "to": [
                {
                    "id": "BSCC-1951-48-20-B397",
                    "short_id": "B397"
                }
            ],
            "what": [
                {
                    "id": "BSCC-1951-48-20-C258",
                    "short_id": "C258"
                },
                {
                    "id": "BSCC-1951-48-20-C684",
                    "short_id": "C684"
                },
                {
                    "id": "BSCC-1951-48-20-C726",
                    "short_id": "C726"
                },
                {
                    "id": "BSCC-1951-48-20-C730",
                    "short_id": "C730"
                },
                {
                    "id": "BSCC-1951-48-20-C737",
                    "short_id": "C737"
                }
            ],
            "description": "The british company A784 trades with the swiss company B397 in the goods C258 and C684 and C726 and C730 and C737"
        }
    ],
    "organisation": [
        {
            "transcription": "Glenfield & Kennedy Ltd."
        }
    ],
    "location": [
        {
            "id": "2645605",
            "lat": "55.61171",
            "lng": "-4.49581",
            "country": {
                "id": "2635167",
                "inferred": "United Kingdom",
                "code": "GB"
            },
            "scheme": "geonames.org",
            "inferred": "Kilmarnock",
            "transcription": " Kilmarnock. "
        }
    ],
    "meta": {
        "version": 1,
        "partOf": "BSCC-1951",
        "generated": "2022-10-26",
        "actions": [
            {
                "actor": {
                    "id": "0000-0002-9541-1202",
                    "scheme": "ORCID",
                    "name": "Sorin Marti"
                },
                "date": "2022-10-26",
                "summary": "Parsed by v.2021-10-31-0 of the BSCC-Parser",
                "classifiedAction": "auto_parse_bscc"
            }
        ]
    }
}