{
    "$schema": [
        "http://schemata.hasdai.org/historic-persons/historic-company-entry-v1.0.1.json"
    ],
    "id": "BSCC-134-1951-1-B522",
    "status": "bscc entry",
    "date": {
        "ref": "1951"
    },
    "transcription": {
        "original": "522. Munkacsi, 3, St. Albananlage, Basle. A 1037, C 162, 959, 967, 1032.",
        "corrected": "522. Munkacsi, 3, St. Albananlage, Basle. A 1037, C 162, 959, 967, 1032"
    },
    "source": {
        "id": "PLEASE_FILL_IN",
        "title": "INDEX OF SWISS AGENTS REPRESENTING UNITED KINGDOM FIRMS",
        "selector": {
            "page": 134,
            "canvas": "http://localhost:8182/iiif/3/0134.jpg/full/max/0/default.jpg",
            "fragment": "http://localhost:8182/iiif/3/0134.jpg/187,308,1276,40/max/0/default.jpg",
            "xywh": "187, 308, 1276, 40"
        }
    },
    "short_id": "B522",
    "label": "Munkacsi",
    "connection": [
        {
            "to": [
                {
                    "id": "BSCC-1951-134-1-A1037",
                    "short_id": "A1037"
                }
            ],
            "what": [
                {
                    "id": "BSCC-1951-134-1-C162",
                    "short_id": "C162"
                },
                {
                    "id": "BSCC-1951-134-1-C959",
                    "short_id": "C959"
                },
                {
                    "id": "BSCC-1951-134-1-C967",
                    "short_id": "C967"
                },
                {
                    "id": "BSCC-1951-134-1-C1032",
                    "short_id": "C1032"
                }
            ],
            "description": "The swiss company B522 trades with the british company A1037 in the goods C162 and C959 and C967 and C1032"
        }
    ],
    "organisation": [
        {
            "transcription": "Munkacsi"
        }
    ],
    "location": [
        {
            "id": "2661604",
            "lat": "47.55839",
            "lng": "7.57327",
            "country": {
                "id": "2658434",
                "inferred": "Switzerland",
                "code": "CH"
            },
            "scheme": "geonames.org",
            "inferred": "Basel",
            "transcription": "3, St. Albananlage, Basle. "
        }
    ],
    "meta": {
        "version": 1,
        "partOf": "BSCC-1951",
        "generated": "2022-10-26",
        "actions": [
            {
                "actor": {
                    "id": "0000-0002-9541-1202",
                    "scheme": "ORCID",
                    "name": "Sorin Marti"
                },
                "date": "2022-10-26",
                "summary": "Parsed by v.2021-10-31-0 of the BSCC-Parser",
                "classifiedAction": "auto_parse_bscc"
            }
        ]
    }
}