{
    "$schema": [
        "http://schemata.hasdai.org/historic-persons/historic-company-entry-v1.0.1.json"
    ],
    "id": "BSCC-46-1951-18-A739",
    "status": "bscc entry",
    "date": {
        "ref": "1951"
    },
    "transcription": {
        "original": "739. Fry's Metal Foundries Ltd., London SW 19. B 249, C 438, 441.",
        "corrected": "739. Fry's Metal Foundries Ltd., London SW 19. B 249, C 438, 441"
    },
    "source": {
        "id": "PLEASE_FILL_IN",
        "title": "INDEX OF SWISS AGENTS REPRESENTING UNITED KINGDOM FIRMS",
        "selector": {
            "page": 46,
            "canvas": "http://localhost:8182/iiif/3/0046.jpg/full/max/0/default.jpg",
            "fragment": "http://localhost:8182/iiif/3/0046.jpg/190,1043,1256,41/max/0/default.jpg",
            "xywh": "190, 1043, 1256, 41"
        }
    },
    "short_id": "A739",
    "label": "Fry's Metal Foundries Ltd.",
    "connection": [
        {
            "to": [
                {
                    "id": "BSCC-1951-46-18-B249",
                    "short_id": "B249"
                }
            ],
            "what": [
                {
                    "id": "BSCC-1951-46-18-C438",
                    "short_id": "C438"
                },
                {
                    "id": "BSCC-1951-46-18-C441",
                    "short_id": "C441"
                }
            ],
            "description": "The british company A739 trades with the swiss company B249 in the goods C438 and C441"
        }
    ],
    "organisation": [
        {
            "transcription": "Fry's Metal Foundries Ltd."
        }
    ],
    "location": [
        {
            "id": "2643743",
            "lat": "51.50853",
            "lng": "-0.12574",
            "country": {
                "id": "2635167",
                "inferred": "United Kingdom",
                "code": "GB"
            },
            "scheme": "geonames.org",
            "inferred": "London",
            "transcription": " London SW 19. "
        }
    ],
    "meta": {
        "version": 1,
        "partOf": "BSCC-1951",
        "generated": "2022-10-26",
        "actions": [
            {
                "actor": {
                    "id": "0000-0002-9541-1202",
                    "scheme": "ORCID",
                    "name": "Sorin Marti"
                },
                "date": "2022-10-26",
                "summary": "Parsed by v.2021-10-31-0 of the BSCC-Parser",
                "classifiedAction": "auto_parse_bscc"
            }
        ]
    }
}