{
    "$schema": [
        "http://schemata.hasdai.org/historic-persons/historic-company-entry-v1.0.1.json"
    ],
    "id": "BSCC-127-1951-14-B330",
    "status": "bscc entry",
    "date": {
        "ref": "1951"
    },
    "transcription": {
        "original": "330. Heumann (A.), Postfach, St. Gall. A 1685, C 246, 248, 332.",
        "corrected": "330. Heumann (A.), Postfach, St. Gall. A 1685, C 246, 248, 332"
    },
    "source": {
        "id": "PLEASE_FILL_IN",
        "title": "INDEX OF SWISS AGENTS REPRESENTING UNITED KINGDOM FIRMS",
        "selector": {
            "page": 127,
            "canvas": "http://localhost:8182/iiif/3/0127.jpg/full/max/0/default.jpg",
            "fragment": "http://localhost:8182/iiif/3/0127.jpg/316,1089,1233,37/max/0/default.jpg",
            "xywh": "316, 1089, 1233, 37"
        }
    },
    "short_id": "B330",
    "label": "Heumann (A.)",
    "connection": [
        {
            "to": [
                {
                    "id": "BSCC-1951-127-14-A1685",
                    "short_id": "A1685"
                }
            ],
            "what": [
                {
                    "id": "BSCC-1951-127-14-C246",
                    "short_id": "C246"
                },
                {
                    "id": "BSCC-1951-127-14-C248",
                    "short_id": "C248"
                },
                {
                    "id": "BSCC-1951-127-14-C332",
                    "short_id": "C332"
                }
            ],
            "description": "The swiss company B330 trades with the british company A1685 in the goods C246 and C248 and C332"
        }
    ],
    "organisation": [
        {
            "transcription": "Heumann (A.)"
        }
    ],
    "location": [
        {
            "transcription": "Postfach, St. Gall. "
        }
    ],
    "meta": {
        "version": 1,
        "partOf": "BSCC-1951",
        "generated": "2022-10-26",
        "actions": [
            {
                "actor": {
                    "id": "0000-0002-9541-1202",
                    "scheme": "ORCID",
                    "name": "Sorin Marti"
                },
                "date": "2022-10-26",
                "summary": "Parsed by v.2021-10-31-0 of the BSCC-Parser",
                "classifiedAction": "auto_parse_bscc"
            }
        ]
    }
}