{
    "$schema": [
        "http://schemata.hasdai.org/historic-persons/historic-company-entry-v1.0.1.json"
    ],
    "id": "BSCC-93-1951-30-A1819",
    "status": "bscc entry",
    "date": {
        "ref": "1951"
    },
    "transcription": {
        "original": "1819. Spencer (George), Moulton & Co. Ltd., London SW 1. B 83, C 1389; B 98, C 794; B 235, C 1414.",
        "corrected": "1819. Spencer (George), Moulton & Co. Ltd., London SW 1.B 83, C 1389; B 98, C 794; B 235, C 1414"
    },
    "source": {
        "id": "PLEASE_FILL_IN",
        "title": "INDEX OF SWISS AGENTS REPRESENTING UNITED KINGDOM FIRMS",
        "selector": {
            "page": 93,
            "canvas": "http://localhost:8182/iiif/3/0093.jpg/full/max/0/default.jpg",
            "fragment": "http://localhost:8182/iiif/3/0093.jpg/355,1569,1183,79/max/0/default.jpg",
            "xywh": "355, 1569, 1183, 79"
        }
    },
    "short_id": "A1819",
    "label": "Spencer (George), Moulton & Co. Ltd.",
    "connection": [
        {
            "to": [
                {
                    "id": "BSCC-1951-93-30-B83",
                    "short_id": "B83"
                }
            ],
            "what": [
                {
                    "id": "BSCC-1951-93-30-C1389",
                    "short_id": "C1389"
                }
            ],
            "description": "The british company A1819 trades with the swiss company B83 in the goods C1389"
        },
        {
            "to": [
                {
                    "id": "BSCC-1951-93-30-B98",
                    "short_id": "B98"
                }
            ],
            "what": [
                {
                    "id": "BSCC-1951-93-30-C794",
                    "short_id": "C794"
                }
            ],
            "description": "The british company A1819 trades with the swiss company B98 in the goods C794"
        },
        {
            "to": [
                {
                    "id": "BSCC-1951-93-30-B235",
                    "short_id": "B235"
                }
            ],
            "what": [
                {
                    "id": "BSCC-1951-93-30-C1414",
                    "short_id": "C1414"
                }
            ],
            "description": "The british company A1819 trades with the swiss company B235 in the goods C1414"
        }
    ],
    "organisation": [
        {
            "transcription": "Spencer (George), Moulton & Co. Ltd."
        }
    ],
    "location": [
        {
            "id": "2643743",
            "lat": "51.50853",
            "lng": "-0.12574",
            "country": {
                "id": "2635167",
                "inferred": "United Kingdom",
                "code": "GB"
            },
            "scheme": "geonames.org",
            "inferred": "London",
            "transcription": " London SW 1."
        }
    ],
    "meta": {
        "version": 1,
        "partOf": "BSCC-1951",
        "generated": "2022-10-26",
        "actions": [
            {
                "actor": {
                    "id": "0000-0002-9541-1202",
                    "scheme": "ORCID",
                    "name": "Sorin Marti"
                },
                "date": "2022-10-26",
                "summary": "Parsed by v.2021-10-31-0 of the BSCC-Parser",
                "classifiedAction": "auto_parse_bscc"
            }
        ]
    }
}