{
    "$schema": [
        "http://schemata.hasdai.org/historic-persons/historic-company-entry-v1.0.1.json"
    ],
    "id": "BSCC-167-1951-39-C616",
    "status": "bscc entry",
    "date": {
        "ref": "1951"
    },
    "transcription": {
        "original": "616. Connecting-rod aligners. A 1935, B 676.",
        "corrected": "616. Connecting-rod aligners. A 1935, B 676"
    },
    "source": {
        "id": "PLEASE_FILL_IN",
        "title": "INDEX OF SWISS AGENTS REPRESENTING UNITED KINGDOM FIRMS",
        "selector": {
            "page": 167,
            "canvas": "http://localhost:8182/iiif/3/0167.jpg/full/max/0/default.jpg",
            "fragment": "http://localhost:8182/iiif/3/0167.jpg/346,2024,1229,38/max/0/default.jpg",
            "xywh": "346, 2024, 1229, 38"
        }
    },
    "short_id": "C616",
    "label": "",
    "connection": [
        {
            "to": [
                {
                    "id": "BSCC-1951-167-39-A1935",
                    "short_id": "A1935"
                },
                {
                    "id": "BSCC-1951-167-39-B676",
                    "short_id": "B676"
                }
            ],
            "description": "with the british company A1935"
        }
    ],
    "organisation": [],
    "location": [],
    "meta": {
        "version": 1,
        "partOf": "BSCC-1951",
        "generated": "2022-10-26",
        "actions": [
            {
                "actor": {
                    "id": "0000-0002-9541-1202",
                    "scheme": "ORCID",
                    "name": "Sorin Marti"
                },
                "date": "2022-10-26",
                "summary": "Parsed by v.2021-10-31-0 of the BSCC-Parser",
                "classifiedAction": "auto_parse_bscc"
            }
        ]
    }
}