{
    "$schema": [
        "http://schemata.hasdai.org/historic-persons/historic-company-entry-v1.0.1.json"
    ],
    "id": "BSCC-86-1951-37-A1640",
    "status": "bscc entry",
    "date": {
        "ref": "1951"
    },
    "transcription": {
        "original": "1640. Ripley Mfg. Co. Ltd., Ripley. B 452, C 1147.",
        "corrected": "1640. Ripley Mfg. Co. Ltd., Ripley. B 452, C 1147"
    },
    "source": {
        "id": "PLEASE_FILL_IN",
        "title": "INDEX OF SWISS AGENTS REPRESENTING UNITED KINGDOM FIRMS",
        "selector": {
            "page": 86,
            "canvas": "http://localhost:8182/iiif/3/0086.jpg/full/max/0/default.jpg",
            "fragment": "http://localhost:8182/iiif/3/0086.jpg/171,1783,1280,40/max/0/default.jpg",
            "xywh": "171, 1783, 1280, 40"
        }
    },
    "short_id": "A1640",
    "label": "Ripley Mfg. Co. Ltd.",
    "connection": [
        {
            "to": [
                {
                    "id": "BSCC-1951-86-37-B452",
                    "short_id": "B452"
                }
            ],
            "what": [
                {
                    "id": "BSCC-1951-86-37-C1147",
                    "short_id": "C1147"
                }
            ],
            "description": "The british company A1640 trades with the swiss company B452 in the goods C1147"
        }
    ],
    "organisation": [
        {
            "transcription": "Ripley Mfg. Co. Ltd."
        }
    ],
    "location": [
        {
            "id": "2639325",
            "lat": "53.03333",
            "lng": "-1.4",
            "country": {
                "id": "2635167",
                "inferred": "United Kingdom",
                "code": "GB"
            },
            "scheme": "geonames.org",
            "inferred": "Ripley",
            "transcription": " Ripley. "
        }
    ],
    "meta": {
        "version": 1,
        "partOf": "BSCC-1951",
        "generated": "2022-10-26",
        "actions": [
            {
                "actor": {
                    "id": "0000-0002-9541-1202",
                    "scheme": "ORCID",
                    "name": "Sorin Marti"
                },
                "date": "2022-10-26",
                "summary": "Parsed by v.2021-10-31-0 of the BSCC-Parser",
                "classifiedAction": "auto_parse_bscc"
            }
        ]
    }
}