{
    "$schema": [
        "http://schemata.hasdai.org/historic-persons/historic-company-entry-v1.0.1.json"
    ],
    "id": "BSCC-142-1951-5-B760",
    "status": "bscc entry",
    "date": {
        "ref": "1951"
    },
    "transcription": {
        "original": "˚ 760. Uhlmann-Eyraud (F.) S.A., 28/30, boulevard de la Cluse, Geneva. A 1298, 1478, 1551, 1601, 1614, 1797, C 905, 933, 934, 945, 946, 955.",
        "corrected": "760. Uhlmann-Eyraud (F.) S.A., 28/30, boulevard de la Cluse, Geneva.A 1298, 1478, 1551, 1601, 1614, 1797, C 905, 933, 934, 945, 946, 955"
    },
    "source": {
        "id": "PLEASE_FILL_IN",
        "title": "INDEX OF SWISS AGENTS REPRESENTING UNITED KINGDOM FIRMS",
        "selector": {
            "page": 142,
            "canvas": "http://localhost:8182/iiif/3/0142.jpg/full/max/0/default.jpg",
            "fragment": "http://localhost:8182/iiif/3/0142.jpg/185,579,1294,78/max/0/default.jpg",
            "xywh": "185, 579, 1294, 78"
        }
    },
    "short_id": "B760",
    "label": "Uhlmann-Eyraud (F.) S.A.",
    "connection": [
        {
            "to": [
                {
                    "id": "BSCC-1951-142-5-A1298",
                    "short_id": "A1298"
                },
                {
                    "id": "BSCC-1951-142-5-A1478",
                    "short_id": "A1478"
                },
                {
                    "id": "BSCC-1951-142-5-A1551",
                    "short_id": "A1551"
                },
                {
                    "id": "BSCC-1951-142-5-A1601",
                    "short_id": "A1601"
                },
                {
                    "id": "BSCC-1951-142-5-A1614",
                    "short_id": "A1614"
                },
                {
                    "id": "BSCC-1951-142-5-A1797",
                    "short_id": "A1797"
                }
            ],
            "what": [
                {
                    "id": "BSCC-1951-142-5-C905",
                    "short_id": "C905"
                },
                {
                    "id": "BSCC-1951-142-5-C933",
                    "short_id": "C933"
                },
                {
                    "id": "BSCC-1951-142-5-C934",
                    "short_id": "C934"
                },
                {
                    "id": "BSCC-1951-142-5-C945",
                    "short_id": "C945"
                },
                {
                    "id": "BSCC-1951-142-5-C946",
                    "short_id": "C946"
                },
                {
                    "id": "BSCC-1951-142-5-C955",
                    "short_id": "C955"
                }
            ],
            "description": "The swiss company B760 trades with the british company A1298 and A1478 and A1551 and A1601 and A1614 and A1797 in the goods C905 and C933 and C934 and C945 and C946 and C955"
        }
    ],
    "organisation": [
        {
            "transcription": "Uhlmann-Eyraud (F.) S.A."
        }
    ],
    "location": [
        {
            "id": "2660646",
            "lat": "46.20222",
            "lng": "6.14569",
            "country": {
                "id": "2658434",
                "inferred": "Switzerland",
                "code": "CH"
            },
            "scheme": "geonames.org",
            "inferred": "Geneva",
            "transcription": " 28/30, boulevard de la Cluse, Geneva."
        }
    ],
    "meta": {
        "version": 1,
        "partOf": "BSCC-1951",
        "generated": "2022-10-26",
        "actions": [
            {
                "actor": {
                    "id": "0000-0002-9541-1202",
                    "scheme": "ORCID",
                    "name": "Sorin Marti"
                },
                "date": "2022-10-26",
                "summary": "Parsed by v.2021-10-31-0 of the BSCC-Parser",
                "classifiedAction": "auto_parse_bscc"
            }
        ]
    }
}