{
    "$schema": [
        "http://schemata.hasdai.org/historic-persons/historic-company-entry-v1.0.1.json"
    ],
    "id": "BSCC-74-1951-13-A1361",
    "status": "bscc entry",
    "date": {
        "ref": "1951"
    },
    "transcription": {
        "original": "1361. Morris (Philip), (Bradford) Ltd., Bradford. B 695, C 1147.",
        "corrected": "1361. Morris (Philip), (Bradford) Ltd., Bradford. B 695, C 1147"
    },
    "source": {
        "id": "PLEASE_FILL_IN",
        "title": "INDEX OF SWISS AGENTS REPRESENTING UNITED KINGDOM FIRMS",
        "selector": {
            "page": 74,
            "canvas": "http://localhost:8182/iiif/3/0074.jpg/full/max/0/default.jpg",
            "fragment": "http://localhost:8182/iiif/3/0074.jpg/184,933,1249,39/max/0/default.jpg",
            "xywh": "184, 933, 1249, 39"
        }
    },
    "short_id": "A1361",
    "label": "Morris (Philip), (Bradford) Ltd.",
    "connection": [
        {
            "to": [
                {
                    "id": "BSCC-1951-74-13-B695",
                    "short_id": "B695"
                }
            ],
            "what": [
                {
                    "id": "BSCC-1951-74-13-C1147",
                    "short_id": "C1147"
                }
            ],
            "description": "The british company A1361 trades with the swiss company B695 in the goods C1147"
        }
    ],
    "organisation": [
        {
            "transcription": "Morris (Philip), (Bradford) Ltd."
        }
    ],
    "location": [
        {
            "id": "2654993",
            "lat": "53.79391",
            "lng": "-1.75206",
            "country": {
                "id": "2635167",
                "inferred": "United Kingdom",
                "code": "GB"
            },
            "scheme": "geonames.org",
            "inferred": "Bradford",
            "transcription": " Bradford. "
        }
    ],
    "meta": {
        "version": 1,
        "partOf": "BSCC-1951",
        "generated": "2022-10-26",
        "actions": [
            {
                "actor": {
                    "id": "0000-0002-9541-1202",
                    "scheme": "ORCID",
                    "name": "Sorin Marti"
                },
                "date": "2022-10-26",
                "summary": "Parsed by v.2021-10-31-0 of the BSCC-Parser",
                "classifiedAction": "auto_parse_bscc"
            }
        ]
    }
}