{
    "$schema": [
        "http://schemata.hasdai.org/historic-persons/historic-company-entry-v1.0.1.json"
    ],
    "id": "BSCC-129-1951-28-B405",
    "status": "bscc entry",
    "date": {
        "ref": "1951"
    },
    "transcription": {
        "original": "˚ 405. Klinkhoff-Apparate AG., 22, Uraniastrasse, Zurich. A 1063, C 687.",
        "corrected": "405. Klinkhoff-Apparate AG., 22, Uraniastrasse, Zurich. A 1063, C 687"
    },
    "source": {
        "id": "PLEASE_FILL_IN",
        "title": "INDEX OF SWISS AGENTS REPRESENTING UNITED KINGDOM FIRMS",
        "selector": {
            "page": 129,
            "canvas": "http://localhost:8182/iiif/3/0129.jpg/full/max/0/default.jpg",
            "fragment": "http://localhost:8182/iiif/3/0129.jpg/294,2189,1292,78/max/0/default.jpg",
            "xywh": "294, 2189, 1292, 78"
        }
    },
    "short_id": "B405",
    "label": "Klinkhoff-Apparate AG.",
    "connection": [
        {
            "to": [
                {
                    "id": "BSCC-1951-129-28-A1063",
                    "short_id": "A1063"
                }
            ],
            "what": [
                {
                    "id": "BSCC-1951-129-28-C687",
                    "short_id": "C687"
                }
            ],
            "description": "The swiss company B405 trades with the british company A1063 in the goods C687"
        }
    ],
    "organisation": [
        {
            "transcription": "Klinkhoff-Apparate AG."
        }
    ],
    "location": [
        {
            "id": "2657896",
            "lat": "47.36667",
            "lng": "8.55",
            "country": {
                "id": "2658434",
                "inferred": "Switzerland",
                "code": "CH"
            },
            "scheme": "geonames.org",
            "inferred": "Zurich",
            "transcription": " 22, Uraniastrasse, Zurich. "
        }
    ],
    "meta": {
        "version": 1,
        "partOf": "BSCC-1951",
        "generated": "2022-10-26",
        "actions": [
            {
                "actor": {
                    "id": "0000-0002-9541-1202",
                    "scheme": "ORCID",
                    "name": "Sorin Marti"
                },
                "date": "2022-10-26",
                "summary": "Parsed by v.2021-10-31-0 of the BSCC-Parser",
                "classifiedAction": "auto_parse_bscc"
            }
        ]
    }
}